topocalc-0.5.0.dist-info/RECORD
topocalc-0.5.0.dist-info/WHEEL
topocalc-0.5.0.dist-info/entry_points.txt
topocalc-0.5.0.dist-info/METADATA
topocalc-0.5.0.dist-info/AUTHORS.md
topocalc-0.5.0.dist-info/top_level.txt
topocalc-0.5.0.dist-info/LICENSE
topocalc/horizon.py
topocalc/cli.py
topocalc/shade.py
topocalc/skew.py
topocalc/gradient.py
topocalc/viewf.py
topocalc/__init__.py
topocalc/core_c/hor1d.c
topocalc/core_c/topo_core.pyx
topocalc/core_c/topo_core.h
topocalc/core_c/topo_core.c
topocalc/core_c/topo_core.cpython-38-x86_64-linux-gnu.so
topocalc/core_c/__init__.py
topocalc/tests/test_viewf.py
topocalc/tests/test_horizon.py
topocalc/tests/test_gradient.py
topocalc/tests/test_skew.py
topocalc/tests/test_shade.py
topocalc/tests/__init__.py
topocalc/tests/Lakes/qgis_sky_view_factor.tif
topocalc/tests/Lakes/topo.nc
topocalc/tests/Lakes/gold_ipw/gold_dem.ipw
topocalc/tests/Lakes/gold_ipw/make_gold_dem.py
topocalc/tests/Lakes/gold_ipw/README.md
topocalc/tests/Lakes/gold_ipw/gold_gradient16.ipw
topocalc/tests/Lakes/gold_ipw/gold_gradient8.ipw
topocalc/tests/Lakes/gold_ipw/skew/skew_-20.ipw
topocalc/tests/Lakes/gold_ipw/skew/skew_45.ipw
topocalc/tests/Lakes/gold_ipw/skew/skew_0.ipw
topocalc/tests/Lakes/gold_ipw/skew/skew_15.ipw
topocalc/tests/Lakes/gold_ipw/skew/skew_25.ipw
topocalc/tests/Lakes/gold_ipw/skew/skew_-40.ipw
topocalc/tests/Lakes/gold_ipw/skew/skew_-10.ipw
topocalc/tests/Lakes/gold_ipw/skew/skew_5.ipw
topocalc/tests/Lakes/gold_ipw/skew/skew_-35.ipw
topocalc/tests/Lakes/gold_ipw/skew/skew_20.ipw
topocalc/tests/Lakes/gold_ipw/skew/skew_-5.ipw
topocalc/tests/Lakes/gold_ipw/skew/skew_10.ipw
topocalc/tests/Lakes/gold_ipw/skew/skew_-15.ipw
topocalc/tests/Lakes/gold_ipw/skew/make_gold_skew
topocalc/tests/Lakes/gold_ipw/skew/skew_-30.ipw
topocalc/tests/Lakes/gold_ipw/skew/skew_40.ipw
topocalc/tests/Lakes/gold_ipw/skew/skew_35.ipw
topocalc/tests/Lakes/gold_ipw/skew/skew_30.ipw
topocalc/tests/Lakes/gold_ipw/skew/skew_-25.ipw
topocalc/tests/Lakes/gold_ipw/skew/skew_-45.ipw
topocalc/tests/Lakes/gold_ipw/horizon/horizon_100.ipw
topocalc/tests/Lakes/gold_ipw/horizon/horizon_140.ipw
topocalc/tests/Lakes/gold_ipw/horizon/horizon_60.ipw
