Metadata-Version: 2.1
Name: topocalc
Version: 0.5.0
Summary: Topo calculations like gradient and sky view
Home-page: https://github.com/USDA-ARS-NWRC/topocalc
Author: USDA ARS NWRC
Author-email: snow@ars.usda.gov
License: CC0 1.0
Keywords: topocalc
Platform: UNKNOWN
Classifier: Development Status :: 2 - Pre-Alpha
Classifier: Intended Audience :: Developers
Classifier: License :: OSI Approved :: MIT License
Classifier: Natural Language :: English
Classifier: Programming Language :: Python :: 3
Classifier: Programming Language :: Python :: 3.6
Classifier: Programming Language :: Python :: 3.7
Classifier: Programming Language :: Python :: 3.8
Classifier: Programming Language :: Python :: 3.9
Requires-Python: >=3.6
